htool/__init__.py
htool/docs.py
htool/dom.py
htool/misc.py
htool/tags.py
htool/text.py
htool-1.0.1.dist-info/.gitignore
htool-1.0.1.dist-info/LICENSE
htool-1.0.1.dist-info/METADATA
htool-1.0.1.dist-info/WHEEL
htool-1.0.1.dist-info/top_level.txt
htool-1.0.1.dist-info/RECORD
